minty_config/__init__.py
minty_config/config.py
minty_config/parser/__init__.py
minty_config/parser/apache.py
minty_config/parser/base.py
minty_config/store/__init__.py
minty_config/store/base.py
minty_config/store/filestore.py
minty_config/store/redis.py
minty_config-0.0.4.dist-info/METADATA
minty_config-0.0.4.dist-info/RECORD
minty_config-0.0.4.dist-info/WHEEL
minty_config-0.0.4.dist-info/top_level.txt
